cloudproof_fpe-0.2.2.dist-info/METADATA
cloudproof_fpe-0.2.2.dist-info/WHEEL
cloudproof_fpe-0.2.2.dist-info/license_files/LICENSE.md
cloudproof_fpe/__init__.pyi
cloudproof_fpe/__init__.py
cloudproof_fpe/py.typed
cloudproof_fpe/cloudproof_fpe.pyd
cloudproof_fpe-0.2.2.dist-info/RECORD
