Metadata-Version: 2.1
Name: cloudproof_fpe
Version: 0.2.2
Classifier: Programming Language :: Rust
Classifier: Programming Language :: Python :: Implementation :: CPython
Classifier: Programming Language :: Python :: Implementation :: PyPy
Requires-Dist: cffi
License-File: LICENSE.md
Summary: Cosmian Cloudproof FPE library
Author: Théophile Brézot<theophile.brezot@cosmian.com>
Author-email: Théophile Brézot<theophile.brezot@cosmian.com>
Requires-Python: >=3.7
Project-URL: Source Code, https://github.com/cosmian/cloudproof_rust/
